spotify_mcp_vsabmbrazil/__init__.py
spotify_mcp_vsabmbrazil/server.py
spotify_mcp_vsabmbrazil/spotify_api.py
spotify_mcp_vsabmbrazil/utils.py
spotify_mcp_vsabmbrazil-0.2.0.dist-info/METADATA
spotify_mcp_vsabmbrazil-0.2.0.dist-info/WHEEL
spotify_mcp_vsabmbrazil-0.2.0.dist-info/entry_points.txt
spotify_mcp_vsabmbrazil-0.2.0.dist-info/RECORD
